autostruct/__init__.py
autostruct/creator.py
autostruct_tool-0.1.5.dist-info/METADATA
autostruct_tool-0.1.5.dist-info/WHEEL
autostruct_tool-0.1.5.dist-info/entry_points.txt
autostruct_tool-0.1.5.dist-info/top_level.txt
autostruct_tool-0.1.5.dist-info/RECORD
